pycroscope/__init__.py
pycroscope/__main__.py
pycroscope/analysis_lib.py
pycroscope/annotated_types.py
pycroscope/annotations.py
pycroscope/arg_spec.py
pycroscope/ast_annotator.py
pycroscope/asynq_checker.py
pycroscope/asynq_test.toml
pycroscope/asynq_tests.py
pycroscope/attributes.py
pycroscope/boolability.py
pycroscope/checker.py
pycroscope/error_code.py
pycroscope/extensions.py
pycroscope/find_unused.py
pycroscope/format_strings.py
pycroscope/functions.py
pycroscope/implementation.py
pycroscope/importer.py
pycroscope/input_sig.py
pycroscope/maybe_asynq.py
pycroscope/name_check_visitor.py
pycroscope/node_visitor.py
pycroscope/options.py
pycroscope/patma.py
pycroscope/predicates.py
pycroscope/reexport.py
pycroscope/relations.py
pycroscope/runtime.py
pycroscope/safe.py
pycroscope/shared_options.py
pycroscope/signature.py
pycroscope/stacked_scopes.py
pycroscope/suggested_type.py
pycroscope/test.toml
pycroscope/test_analysis_lib.py
pycroscope/test_annotated_types.py
pycroscope/test_annotations.py
pycroscope/test_arg_spec.py
pycroscope/test_ast_annotator.py
pycroscope/test_async_await.py
pycroscope/test_asynq.py
pycroscope/test_asynq_checker.py
pycroscope/test_attributes.py
pycroscope/test_boolability.py
pycroscope/test_config.py
pycroscope/test_definite_value.py
pycroscope/test_deprecated.py
pycroscope/test_enum.py
pycroscope/test_error_code.py
pycroscope/test_extensions.py
pycroscope/test_format_strings.py
pycroscope/test_functions.py
pycroscope/test_generators.py
pycroscope/test_implementation.py
pycroscope/test_import.py
pycroscope/test_inference_helpers.py
pycroscope/test_literal_string.py
pycroscope/test_name_check_visitor.py
pycroscope/test_never.py
pycroscope/test_node_visitor.py
pycroscope/test_operations.py
pycroscope/test_override.py
pycroscope/test_patma.py
pycroscope/test_pep673.py
pycroscope/test_recursion.py
pycroscope/test_relations.py
pycroscope/test_runtime.py
pycroscope/test_self.py
pycroscope/test_signature.py
pycroscope/test_stacked_scopes.py
pycroscope-0.2.0.dist-info/licenses/LICENSE
pycroscope-0.2.0.dist-info/METADATA
pycroscope-0.2.0.dist-info/WHEEL
pycroscope-0.2.0.dist-info/entry_points.txt
pycroscope-0.2.0.dist-info/top_level.txt
pycroscope-0.2.0.dist-info/RECORD
