Metadata-Version: 2.4
Name: pycroscope
Version: 0.2.0
Summary: A static analyzer for Python
Author-email: Jelle Zijlstra <jelle.zijlstra@gmail.com>
License: Apache Software License
Project-URL: Homepage, https://github.com/JelleZijlstra/pycroscope
Keywords: type checker,static analysis
Classifier: License :: OSI Approved :: Apache Software License
Classifier: Programming Language :: Python
Classifier: Programming Language :: Python :: 3.9
Classifier: Programming Language :: Python :: 3.10
Classifier: Programming Language :: Python :: 3.11
Classifier: Programming Language :: Python :: 3.12
Classifier: Programming Language :: Python :: 3.13
Requires-Python: >=3.9
License-File: LICENSE
Requires-Dist: ast_decompiler>=0.4.0
Requires-Dist: typeshed_client>=2.1.0
Requires-Dist: typing_extensions>=4.12.0
Requires-Dist: codemod
Requires-Dist: tomli>=1.1.0
Provides-Extra: tests
Requires-Dist: pytest; extra == "tests"
Requires-Dist: mypy_extensions; extra == "tests"
Requires-Dist: attrs; extra == "tests"
Requires-Dist: pydantic; python_version < "3.14" and extra == "tests"
Requires-Dist: annotated-types; extra == "tests"
Provides-Extra: asynq
Requires-Dist: asynq; extra == "asynq"
Requires-Dist: qcore>=0.5.1; extra == "asynq"
Dynamic: license-file
